{"version": "https://jsonfeed.org/version/1.1", "title": "SYANiDE-.github.io writeups", "home_page_url": "https://syanide-.github.io/writeups/", "feed_url": "https://syanide-.github.io/writeups/feed_json_updated.json", "description": null, "icon": null, "authors": [], "language": "en", "items": [{"id": "https://syanide-.github.io/writeups/blog/2025/11/13/2025-11-13-how-i-operate-within-a-kerberos-realm/", "url": "https://syanide-.github.io/writeups/blog/2025/11/13/2025-11-13-how-i-operate-within-a-kerberos-realm/", "title": "2025 11 13 How I Operate Within a Kerberos Realm", "content_html": "<p>When I am working in a Kerberos realm, there are a few things I do as a collection of standard procedure on any given engagement.</p>\n<ol>\n<li><code>/etc/hosts</code>: Add hostn...</li>\n</ol>", "image": null, "date_modified": "2025-11-14T05:47:18+00:00", "date_published": "2025-11-13T00:00:00+00:00", "authors": [], "tags": []}]}